ClickUpShiftScore/__init__.py
ClickUpShiftScore/_nbdev.py
ClickUpShiftScore/core.py
ClickUpShiftScore/helper.py
ClickUpShiftScore-0.0.1.dist-info/LICENSE
ClickUpShiftScore-0.0.1.dist-info/METADATA
ClickUpShiftScore-0.0.1.dist-info/WHEEL
ClickUpShiftScore-0.0.1.dist-info/top_level.txt
ClickUpShiftScore-0.0.1.dist-info/RECORD
